MANIFEST.in
README.txt
setup.py
TransFabric/TransFabric.py
TransFabric/_TransFabric.so
TransFabric/__init__.py
TransFabric_Python2X_Linux_x64.egg-info/PKG-INFO
TransFabric_Python2X_Linux_x64.egg-info/SOURCES.txt
TransFabric_Python2X_Linux_x64.egg-info/dependency_links.txt
TransFabric_Python2X_Linux_x64.egg-info/top_level.txt