Metadata-Version: 1.1
Name: TransFabric-Python2X-Linux-x64
Version: 1.0
Summary: TransFabric Parser for Python 2X, for hardware Linux-x64
Home-page: UNKNOWN
Author: TransFabric Ltd
Author-email: UNKNOWN
License: UNKNOWN
Platform: 
Classifier: Classifier: Development Status :: 2 - Pre-Alpha
Classifier: Classifier: License :: Free for non-commercial use
Classifier: Classifier: Natural Language :: English
Classifier: Classifier: Topic :: Software Development :: Libraries
